lmitf/__init__.py
lmitf/agent_llm.py
lmitf/base_llm.py
lmitf/base_lvm.py
lmitf/templete_llm.py
lmitf/test_agent_llm.py
lmitf/utils.py
lmitf/datasets/manager.py
lmitf/datasets/llm_prompts/text2triples.py
lmitf/datasets/lvm_prompts/character_ref.png
lmitf/datasets/lvm_prompts/character_ref.py
lmitf/pricing/__init__.py
lmitf/pricing/fetch_dmxapi.py
lmitf/template_lvm/__init__.py
lmitf/template_lvm/storyboard.py
lmitf/tests/__init__.py
lmitf/tests/conftest.py
lmitf/tests/test_edge_cases.py
lmitf/tests/test_init.py
lmitf/tests/test_llm.py
lmitf/tests/test_lvm.py
lmitf/tests/test_manager.py
lmitf/tests/test_price.py
lmitf/tests/test_template_llm.py
lmitf/tests/test_utils.py
lmitf-0.1.24.dist-info/licenses/LICENSE
lmitf-0.1.24.dist-info/WHEEL
lmitf-0.1.24.dist-info/METADATA
lmitf-0.1.24.dist-info/RECORD
