Metadata-Version: 2.4
Name: lmitf
Version: 0.1.24
Summary: Large Model Interface - A flexible interface for interacting with large language models and vision models.
Keywords: ai,llm,lvm,api,interface,openai,large-model
Author-email: Guohao Zhang <guohao2045@gmail.com>
Requires-Python: >=3.10
Classifier: Development Status :: 3 - Alpha
Classifier: Intended Audience :: Developers
Classifier: License :: OSI Approved :: MIT License
Classifier: Programming Language :: Python :: 3
Classifier: Programming Language :: Python :: 3.10
Classifier: Programming Language :: Python :: 3.11
Classifier: Programming Language :: Python :: 3.12
Classifier: Topic :: Software Development :: Libraries :: Python Modules
Classifier: Topic :: Scientific/Engineering :: Artificial Intelligence
License-File: LICENSE
Requires-Dist: openai>=1.0
Requires-Dist: pandas>=2.3
Requires-Dist: python-dotenv>=1.0
Requires-Dist: wasabi>=1.1
Requires-Dist: pillow>=9.0
Requires-Dist: python-docx>=1.2.0
Project-URL: Homepage, https://github.com/colehank/AI-interface
Project-URL: Issues, https://github.com/colehank/AI-interface/issues
Project-URL: Repository, https://github.com/colehank/AI-interface
